{
    "fileFormatVersion": "1",
    "parameterSets": {
        "New set 1": {
            "base": "4",
            "base_h": "5",
            "base_w": "40",
            "coupler_length": "12",
            "coupler_outer_d": "10",
            "coupler_with_slit": "true",
            "mount_hole_d": "3.3999999999999999",
            "mount_hole_inset": "4",
            "mount_y": "2",
            "show_base": "true",
            "show_coupler": "false",
            "show_motor": "false",
            "show_mount": "true",
            "tolerance": "0.29999999999999999",
            "wall": "2.5"
        },
        "New set 2": {
            "base": "4",
            "base_h": "5",
            "base_w": "40",
            "coupler_length": "12",
            "coupler_outer_d": "10",
            "coupler_with_slit": "true",
            "mount_hole_d": "3.3999999999999999",
            "mount_hole_inset": "4",
            "mount_y": "0",
            "show_base": "true",
            "show_coupler": "true",
            "show_motor": "true",
            "show_mount": "true",
            "tolerance": "0.29999999999999999",
            "wall": "2.5"
        }
    }
}
